MANIFEST.in
README.md
setup.py
andrew/__init__.py
andrew.egg-info/PKG-INFO
andrew.egg-info/SOURCES.txt
andrew.egg-info/dependency_links.txt
andrew.egg-info/not-zip-safe
andrew.egg-info/top_level.txt