Metadata-Version: 1.0
Name: andrew
Version: 0.1
Summary: the portable Andrew
Home-page: https://github.com/rueberger/andrew
Author: Andrew Berger
Author-email: andbberger@gmail.com
License: MIT
Platform: UNKNOWN
